sphinx_toggleprompt/__init__.py
sphinx_toggleprompt/_static/toggleprompt.js_t
sphinx_toggleprompt-0.6.0.dist-info/LICENSE
sphinx_toggleprompt-0.6.0.dist-info/METADATA
sphinx_toggleprompt-0.6.0.dist-info/WHEEL
sphinx_toggleprompt-0.6.0.dist-info/top_level.txt
sphinx_toggleprompt-0.6.0.dist-info/RECORD
