Metadata-Version: 2.2
Name: sphinx-toggleprompt
Version: 0.6.0
Summary: Add a python prompt toggle to each code cell.
Home-page: https://github.com/jurasofish/sphinx-toggleprompt
Author: Michael Jurasovic
License: MIT License
Classifier: License :: OSI Approved :: MIT License
Requires-Python: >=3.9
License-File: LICENSE
Requires-Dist: sphinx>=5.0.0
Dynamic: author
Dynamic: classifier
Dynamic: description
Dynamic: description-content-type
Dynamic: home-page
Dynamic: license
Dynamic: requires-dist
Dynamic: requires-python
Dynamic: summary
